strledger/__init__.py
strledger/cli.py
strledger/core.py
strledger/py.typed
strledger-0.10.1.dist-info/LICENSE
strledger-0.10.1.dist-info/METADATA
strledger-0.10.1.dist-info/WHEEL
strledger-0.10.1.dist-info/entry_points.txt
strledger-0.10.1.dist-info/RECORD
