Metadata-Version: 2.3
Name: strledger
Version: 0.10.1
Summary: Ledger Hardware Wallet Stellar Python bindings.
License: MIT
Keywords: stellar,ledger
Author: overcat
Author-email: 4catcode@gmail.com
Requires-Python: >=3.9,<4.0
Classifier: Development Status :: 4 - Beta
Classifier: License :: OSI Approved :: MIT License
Classifier: Natural Language :: English
Classifier: Operating System :: OS Independent
Classifier: Programming Language :: Python
Classifier: Programming Language :: Python :: 3
Classifier: Programming Language :: Python :: 3.9
Classifier: Programming Language :: Python :: 3.10
Classifier: Programming Language :: Python :: 3.11
Classifier: Programming Language :: Python :: 3.12
Classifier: Programming Language :: Python :: 3.13
Classifier: Programming Language :: Python :: 3 :: Only
Classifier: Typing :: Typed
Requires-Dist: click (>=8.1.7)
Requires-Dist: ledgerwallet (>=0.5.1)
Requires-Dist: stellar-sdk (>=12.0.0)
Project-URL: Bug Tracker, https://github.com/lightsail-network/strledger/issues
Project-URL: Documentation, https://github.com/lightsail-network/strledger
Project-URL: Homepage, https://github.com/lightsail-network/strledger
Project-URL: Repository, https://github.com/lightsail-network/strledger
